<?xml version="1.0" encoding="UTF-8"?><record_update sys_domain="global" table="sysevent_email_action">
    <sysevent_email_action action="INSERT_OR_UPDATE">
        <action_insert>false</action_insert>
        <action_update>false</action_update>
        <active>true</active>
        <advanced_condition/>
        <affected_field_on_event/>
        <category display_value="Uncategorized" name="Uncategorized">c97d83137f4432005f58108c3ffa917a</category>
        <collection>x_1173448_contra_0_candidatura</collection>
        <condition/>
        <content_type>text/html</content_type>
        <default_interval/>
        <description>formulário 3</description>
        <digest_from/>
        <digest_html/>
        <digest_reply_to/>
        <digest_separator_html><![CDATA[<br><hr><br>]]></digest_separator_html>
        <digest_separator_text><![CDATA[\n--------------------------------------------------------------------------------\n]]></digest_separator_text>
        <digest_subject/>
        <digest_template/>
        <digest_text/>
        <digestable>false</digestable>
        <enable_dynamic_translation>false</enable_dynamic_translation>
        <event_name/>
        <event_parm_1>false</event_parm_1>
        <event_parm_2>false</event_parm_2>
        <exclude_delegates>false</exclude_delegates>
        <force_delivery>false</force_delivery>
        <from/>
        <generation_type>triggered</generation_type>
        <importance/>
        <include_attachments>false</include_attachments>
        <item>event.parm1</item>
        <item_table/>
        <mandatory>false</mandatory>
        <message/>
        <message_html><![CDATA[<p>Prezado ${nome},</p>
<p>Parab&eacute;ns pela sua aprova&ccedil;&atilde;o nas etapas anteriores do processo seletivo para a posi&ccedil;&atilde;o de Desenvolvedor. Estamos entusiasmados para continuar com a avalia&ccedil;&atilde;o do seu perfil e gostar&iacute;amos de agendar uma entrevista pessoal com voc&ecirc;.</p>
<p>Para escolher a data da sua entrevista, acesse o formul&aacute;rio de agendamento no seguinte link: <a title="Acessar formul&aacute;rio" href="https://dev90474.service-now.com/com.glideapp.servicecatalog_cat_item_view.do?v=1&amp;sysparm_id=eeeed8df97063110489d747e6253af18" target="_blank" rel="noopener">https://dev90474.service-now.com/com.glideapp.servicecatalog_cat_item_view.do?v=1&amp;sysparm_id=eeeed8df97063110489d747e6253af18</a></p>
<p>Neste formul&aacute;rio, voc&ecirc; encontrar&aacute; as seguintes op&ccedil;&otilde;es de data para a entrevista:</p>
<ul style="list-style-type: disc; list-style-position: inside;">
<li>Data 1: ${data_1}</li>
<li>Data 2: ${data_2}</li>
<li>Data 3: ${data_3}</li>
</ul>
<p>Por favor, selecione a data que melhor se ajusta &agrave; sua agenda. Caso nenhuma das datas seja conveniente, voc&ecirc; pode inserir uma data alternativa no campo fornecido.</p>
<p>Prazo para a escolha da data e de 1 dia.</p>
<p>Agradecemos antecipadamente pela sua coopera&ccedil;&atilde;o e estamos ansiosos para conhec&ecirc;-lo pessoalmente.</p>
<p>Atenciosamente,&nbsp;</p>
<p>Atendente</p>]]></message_html>
        <message_list/>
        <message_text/>
        <name>Escolha a data da primeira entrevista</name>
        <omit_watermark>false</omit_watermark>
        <order>100</order>
        <push_message_only>false</push_message_only>
        <recipient_fields>e_mail</recipient_fields>
        <recipient_groups/>
        <recipient_users/>
        <reply_to/>
        <send_self>false</send_self>
        <sms_alternate/>
        <style/>
        <subject>Próxima Etapa - Escolha de Data de Entrevista</subject>
        <subscribable>false</subscribable>
        <sys_class_name>sysevent_email_action</sys_class_name>
        <sys_created_by>admin</sys_created_by>
        <sys_created_on>2023-10-28 03:49:47</sys_created_on>
        <sys_domain>global</sys_domain>
        <sys_domain_path>/</sys_domain_path>
        <sys_id>be00a1df970a3110489d747e6253afa3</sys_id>
        <sys_mod_count>0</sys_mod_count>
        <sys_name>Escolha a data da primeira entrevista</sys_name>
        <sys_overrides/>
        <sys_package display_value="Contratação" source="x_1173448_contra_0">2f98045b97c23110489d747e6253afec</sys_package>
        <sys_policy/>
        <sys_scope display_value="Contratação">2f98045b97c23110489d747e6253afec</sys_scope>
        <sys_update_name>sysevent_email_action_be00a1df970a3110489d747e6253afa3</sys_update_name>
        <sys_updated_by>admin</sys_updated_by>
        <sys_updated_on>2023-10-28 03:49:47</sys_updated_on>
        <sys_version>2</sys_version>
        <template/>
        <type>email</type>
        <weight>0</weight>
    </sysevent_email_action>
</record_update>
